mlarray/__init__.py
mlarray/cli.py
mlarray/meta.py
mlarray/mlarray.py
mlarray/utils.py
mlarray-0.0.33.data/data/mlarray/assets/banner.png
mlarray-0.0.33.data/data/mlarray/assets/banner.png~
mlarray-0.0.33.dist-info/licenses/LICENSE
mlarray-0.0.33.dist-info/METADATA
mlarray-0.0.33.dist-info/WHEEL
mlarray-0.0.33.dist-info/entry_points.txt
mlarray-0.0.33.dist-info/top_level.txt
mlarray-0.0.33.dist-info/RECORD
