Metadata-Version: 2.4
Name: mlarray
Version: 0.0.33
Summary: Array format specialized for Machine Learning with Blosc2 backend and standardized metadata.
Author-email: Karol Gotkowski <karol.gotkowski@dkfz.de>
License: MIT
Project-URL: Homepage, https://github.com/MIC-DKFZ/mlarray
Project-URL: Source, https://github.com/MIC-DKFZ/mlarray
Project-URL: Issues, https://github.com/MIC-DKFZ/mlarray/issues
Keywords: copier,template,python
Classifier: Programming Language :: Python :: 3
Classifier: Programming Language :: Python :: 3.10
Classifier: Programming Language :: Python :: 3.11
Classifier: Programming Language :: Python :: 3.12
Classifier: Operating System :: OS Independent
Requires-Python: >=3.10
License-File: LICENSE
Requires-Dist: blosc2>=3
Requires-Dist: numpy>=2
Provides-Extra: dev
Requires-Dist: build>=1.0; extra == "dev"
Requires-Dist: pytest>=7.0; extra == "dev"
Requires-Dist: twine>=4.0; extra == "dev"
Requires-Dist: setuptools_scm[toml]>=8.0; extra == "dev"
Provides-Extra: docs
Requires-Dist: mkdocs-material>=9.5; extra == "docs"
Requires-Dist: mkdocs-include-markdown-plugin>=6.0; extra == "docs"
Requires-Dist: mkdocstrings[python]>=0.25; extra == "docs"
Requires-Dist: pymdown-extensions>=10.0; extra == "docs"
Provides-Extra: all
Requires-Dist: medvol; extra == "all"
Dynamic: license-file
